nautical_calculations/__init__.py
nautical_calculations/__main__.py
nautical_calculations/basic.py
nautical_calculations/operations.py
nautical_calculations-1.0.1.dist-info/METADATA
nautical_calculations-1.0.1.dist-info/WHEEL
nautical_calculations-1.0.1.dist-info/entry_points.txt
nautical_calculations-1.0.1.dist-info/top_level.txt
nautical_calculations-1.0.1.dist-info/RECORD
