Metadata-Version: 2.1
Name: nautical-calculations
Version: 1.0.1
Summary: Get all the nautical calculations here. 
Home-page: https://github.com/AmeyHengle/nautical_calculations
Author: Amey Hengle
Author-email: domainamey@gmail.com
License: MIT
Platform: UNKNOWN
Classifier: License :: OSI Approved :: MIT License
Classifier: Programming Language :: Python :: 3
Classifier: Programming Language :: Python :: 3.7
Requires-Python: >=3.6
